wcheck/__init__.py
wcheck/gui.py
wcheck/tui.py
wcheck/wcheck.py
wcheck-0.5.4.dist-info/METADATA
wcheck-0.5.4.dist-info/WHEEL
wcheck-0.5.4.dist-info/entry_points.txt
wcheck-0.5.4.dist-info/licenses/LICENSE
wcheck-0.5.4.dist-info/RECORD
