Metadata-Version: 2.4
Name: wcheck
Version: 0.5.4
Summary: Manage a workspace of git repositories
Project-URL: Homepage, https://github.com/PastorD/wcheck
Project-URL: Documentation, https://pastord.github.io/wcheck/
Project-URL: Repository, https://github.com/PastorD/wcheck
Project-URL: Issues, https://github.com/PastorD/wcheck/issues
Project-URL: Changelog, https://github.com/PastorD/wcheck/blob/main/CHANGELOG.md
Author-email: Daniel Pastor <danpasmor@gmail.com>
License-Expression: MIT
License-File: LICENSE
Keywords: git,repository,version-control,workspace
Classifier: Development Status :: 4 - Beta
Classifier: Environment :: Console
Classifier: Intended Audience :: Developers
Classifier: License :: OSI Approved :: MIT License
Classifier: Operating System :: POSIX :: Linux
Classifier: Programming Language :: Python :: 3
Classifier: Topic :: Software Development :: Version Control :: Git
Requires-Python: <3.13,>=3.9
Requires-Dist: click>=8.0.0
Requires-Dist: gitpython>=3.1.29
Requires-Dist: pendulum>=3.0.0
Requires-Dist: pyyaml>=6.0
Requires-Dist: rich>=12.6.0
Provides-Extra: dev
Requires-Dist: mypy>=1.15.0; extra == 'dev'
Requires-Dist: pytest>=8.3.4; extra == 'dev'
Requires-Dist: ruff>=0.9.9; extra == 'dev'
Provides-Extra: docs
Requires-Dist: mkdocs-material>=9.5.0; extra == 'docs'
Requires-Dist: mkdocs>=1.6.0; extra == 'docs'
Requires-Dist: mkdocstrings[python]>=0.24.0; extra == 'docs'
Provides-Extra: gui
Requires-Dist: pyside6>=6.4.0; extra == 'gui'
Provides-Extra: tui
Requires-Dist: textual>=0.50.0; extra == 'tui'
